tryit/__init__.py
tryit/core.py
tryit-0.1.2.dist-info/LICENSE
tryit-0.1.2.dist-info/WHEEL
tryit-0.1.2.dist-info/METADATA
tryit-0.1.2.dist-info/RECORD
