Metadata-Version: 2.1
Name: tryit
Version: 0.1.2
Summary: 
Author: Mario A. Visca
Author-email: mvisca89@gmail.com
Requires-Python: >=3.9
Classifier: Programming Language :: Python :: 3
Classifier: Programming Language :: Python :: 3.9
Classifier: Programming Language :: Python :: 3.10
